pagetreeepub/__init__.py
pagetreeepub/models.py
pagetreeepub/renderers.py
pagetreeepub/views.py
django_pagetree_epub-0.3.0.dist-info/METADATA
django_pagetree_epub-0.3.0.dist-info/WHEEL
django_pagetree_epub-0.3.0.dist-info/top_level.txt
django_pagetree_epub-0.3.0.dist-info/RECORD
