Metadata-Version: 2.1
Name: django-pagetree-epub
Version: 0.3.0
Summary: make an epub from a pagetree site
Home-page: https://github.com/ccnmtl/django-pagetree-epub
Author: Anders Pearson
Author-email: ctl-dev@columbia.edu
License: BSD
Platform: any
Requires-Dist: Django (>=1.8)
Requires-Dist: nose
Requires-Dist: django-pagetree
Requires-Dist: epubbuilder
